ChemSpaceAL/ALConstruction.py
ChemSpaceAL/Configuration.py
ChemSpaceAL/Dataset.py
ChemSpaceAL/Docking.py
ChemSpaceAL/Generation.py
ChemSpaceAL/InitializeWorkspace.py
ChemSpaceAL/Model.py
ChemSpaceAL/Sampling.py
ChemSpaceAL/Scoring.py
ChemSpaceAL/Training.py
ChemSpaceAL/__init__.py
ChemSpaceAL-2.0.1.dist-info/LICENSE
ChemSpaceAL-2.0.1.dist-info/METADATA
ChemSpaceAL-2.0.1.dist-info/WHEEL
ChemSpaceAL-2.0.1.dist-info/top_level.txt
ChemSpaceAL-2.0.1.dist-info/RECORD
