Metadata-Version: 2.1
Name: ChemSpaceAL
Version: 2.0.1
Summary: ChemSpaceAL Python package: an efficient active learning methodology applied to protein-specific molecular generation
Home-page: https://github.com/batistagroup/ChemSpaceAL
Download-URL: https://github.com/gregory-kyro/ChemSpaceAL/archive/refs/tags/v1.0.3.tar.gz
Author: Gregory W. Kyro, Anton Morgunov & Rafael I. Brent
Author-email: gregory.kyro@yale.edu
Keywords: active learning,artificial intelligence,deep learning,machine learning,molecular generation,drug discovery
Classifier: Programming Language :: Python :: 3
Classifier: License :: OSI Approved :: MIT License
Classifier: Operating System :: OS Independent
Requires-Python: >=3.10
License-File: LICENSE
Requires-Dist: prolif ==2.0.1
Requires-Dist: pandas ==1.5.3
Requires-Dist: numpy
Requires-Dist: rdkit
Requires-Dist: torch
Requires-Dist: PyYAML
Requires-Dist: scikit-learn
Requires-Dist: tqdm
Requires-Dist: wandb
